TesterhomeWikiQitaHejiFix1/README.md
TesterhomeWikiQitaHejiFix1/__init__.py
TesterhomeWikiQitaHejiFix1/__main__.py
TesterhomeWikiQitaHejiFix1/file.epub
TesterhomeWikiQitaHejiFix1/index.html
TesterhomeWikiQitaHejiFix1/css/__init__.py
TesterhomeWikiQitaHejiFix1/css/annotations.css
TesterhomeWikiQitaHejiFix1/css/main.css
TesterhomeWikiQitaHejiFix1/css/normalize.css
TesterhomeWikiQitaHejiFix1/css/popup.css
TesterhomeWikiQitaHejiFix1/font/__init__.py
TesterhomeWikiQitaHejiFix1/font/fontello.eot
TesterhomeWikiQitaHejiFix1/font/fontello.svg
TesterhomeWikiQitaHejiFix1/font/fontello.ttf
TesterhomeWikiQitaHejiFix1/font/fontello.woff
TesterhomeWikiQitaHejiFix1/img/__init__.py
TesterhomeWikiQitaHejiFix1/img/annotator-glyph-sprite.png
TesterhomeWikiQitaHejiFix1/img/annotator-icon-sprite.png
TesterhomeWikiQitaHejiFix1/img/apple-touch-icon.png
TesterhomeWikiQitaHejiFix1/img/cancelfullscreen.png
TesterhomeWikiQitaHejiFix1/img/close.png
TesterhomeWikiQitaHejiFix1/img/fullscreen.png
TesterhomeWikiQitaHejiFix1/img/loader.gif
TesterhomeWikiQitaHejiFix1/img/menu-icon.png
TesterhomeWikiQitaHejiFix1/img/save.png
TesterhomeWikiQitaHejiFix1/img/saved.png
TesterhomeWikiQitaHejiFix1/img/settings-s.png
TesterhomeWikiQitaHejiFix1/img/settings.png
TesterhomeWikiQitaHejiFix1/img/star.png
TesterhomeWikiQitaHejiFix1/js/__init__.py
TesterhomeWikiQitaHejiFix1/js/epub.js
TesterhomeWikiQitaHejiFix1/js/epub.min.js
TesterhomeWikiQitaHejiFix1/js/epub.min.map
TesterhomeWikiQitaHejiFix1/js/hooks.min.js
TesterhomeWikiQitaHejiFix1/js/hooks.min.map
TesterhomeWikiQitaHejiFix1/js/reader.js
TesterhomeWikiQitaHejiFix1/js/reader.js.map
TesterhomeWikiQitaHejiFix1/js/reader.min.js
TesterhomeWikiQitaHejiFix1/js/reader.min.map
TesterhomeWikiQitaHejiFix1/js/hooks/__init__.py
TesterhomeWikiQitaHejiFix1/js/hooks/extensions/__init__.py
TesterhomeWikiQitaHejiFix1/js/hooks/extensions/highlight.js
TesterhomeWikiQitaHejiFix1/js/libs/__init__.py
TesterhomeWikiQitaHejiFix1/js/libs/jquery.min.js
testerhome_wiki_qita_heji_fix1-2025.3.25.1.dist-info/METADATA
testerhome_wiki_qita_heji_fix1-2025.3.25.1.dist-info/WHEEL
testerhome_wiki_qita_heji_fix1-2025.3.25.1.dist-info/entry_points.txt
testerhome_wiki_qita_heji_fix1-2025.3.25.1.dist-info/top_level.txt
testerhome_wiki_qita_heji_fix1-2025.3.25.1.dist-info/RECORD
